tcmb/__init__.py
tcmb/_data.py
tcmb/auth.py
tcmb/const.py
tcmb/core.py
tcmb/errors.py
tcmb/fetch.py
tcmb/utils.py
tcmb/resources/series.json
tcmb-0.4.0.dist-info/LICENSE
tcmb-0.4.0.dist-info/METADATA
tcmb-0.4.0.dist-info/WHEEL
tcmb-0.4.0.dist-info/top_level.txt
tcmb-0.4.0.dist-info/RECORD
