Metadata-Version: 2.1
Name: tcmb
Version: 0.4.0
Summary: Central Bank of the Republic of Türkiye (TCMB) Python API.
Author-email: Kaymal <gutkyle@gmail.com>
License: MIT License
Project-URL: repository, https://github.com/kaymal/tcmb-py
Project-URL: pypi, https://pypi.org/project/tcmb
Classifier: Operating System :: OS Independent
Classifier: Programming Language :: Python :: 3
Classifier: Programming Language :: Python :: 3.8
Classifier: Programming Language :: Python :: 3.9
Classifier: Programming Language :: Python :: 3.10
Classifier: Programming Language :: Python :: 3.11
Requires-Python: >=3.8
License-File: LICENSE
Requires-Dist: pandas
Requires-Dist: numpy
Requires-Dist: requests
